nhentai/__init__.py
nhentai/nhentai.py
nhentai.py-2.2.1.dist-info/METADATA
nhentai.py-2.2.1.dist-info/WHEEL
nhentai.py-2.2.1.dist-info/top_level.txt
nhentai.py-2.2.1.dist-info/RECORD
