Metadata-Version: 2.1
Name: nhentai.py
Version: 2.2.1
Summary: an nhentai api wrapper.
Home-page: https://github.com/moe-ka/nhentai.py
Author: moka
License: UNKNOWN
Platform: UNKNOWN
